rasterio/control.py
rasterio/coords.py
rasterio/crs.cp310-win_amd64.pyd
rasterio/drivers.py
rasterio/dtypes.py
rasterio/enums.py
rasterio/env.py
rasterio/errors.py
rasterio/features.py
rasterio/fill.py
rasterio/io.py
rasterio/mask.py
rasterio/merge.py
rasterio/path.py
rasterio/plot.py
rasterio/profiles.py
rasterio/rpc.py
rasterio/sample.py
rasterio/session.py
rasterio/shutil.cp310-win_amd64.pyd
rasterio/tools.py
rasterio/transform.py
rasterio/vrt.py
rasterio/warp.py
rasterio/windows.py
rasterio/_base.cp310-win_amd64.pyd
rasterio/_env.cp310-win_amd64.pyd
rasterio/_err.cp310-win_amd64.pyd
rasterio/_example.cp310-win_amd64.pyd
rasterio/_features.cp310-win_amd64.pyd
rasterio/_filepath.cp310-win_amd64.pyd
rasterio/_fill.cp310-win_amd64.pyd
rasterio/_io.cp310-win_amd64.pyd
rasterio/_path.py
rasterio/_show_versions.py
rasterio/_transform.cp310-win_amd64.pyd
rasterio/_version.cp310-win_amd64.pyd
rasterio/_warp.cp310-win_amd64.pyd
rasterio/__init__.py
rasterio/gdal_data/bag_template.xml
rasterio/gdal_data/copyright
rasterio/gdal_data/cubewerx_extra.wkt
rasterio/gdal_data/default.rsc
rasterio/gdal_data/ecw_cs.wkt
rasterio/gdal_data/eedaconf.json
rasterio/gdal_data/epsg.wkt
rasterio/gdal_data/esri_StatePlane_extra.wkt
rasterio/gdal_data/GDAL-targets-debug.cmake
rasterio/gdal_data/GDAL-targets-release.cmake
rasterio/gdal_data/GDAL-targets.cmake
rasterio/gdal_data/GDALConfig.cmake
rasterio/gdal_data/GDALConfigVersion.cmake
rasterio/gdal_data/gdalicon.png
rasterio/gdal_data/gdalinfo_output.schema.json
rasterio/gdal_data/GDALLogoBW.svg
rasterio/gdal_data/GDALLogoColor.svg
rasterio/gdal_data/GDALLogoGS.svg
rasterio/gdal_data/gdalmdiminfo_output.schema.json
rasterio/gdal_data/gdaltileindex.xsd
rasterio/gdal_data/gdalvrt.xsd
rasterio/gdal_data/gfs.xsd
rasterio/gdal_data/gml_registry.xml
rasterio/gdal_data/gml_registry.xsd
rasterio/gdal_data/grib2_center.csv
rasterio/gdal_data/grib2_process.csv
rasterio/gdal_data/grib2_subcenter.csv
rasterio/gdal_data/grib2_table_4_2_0_0.csv
geoai_rasterio-1.3.11.dist-info/AUTHORS.txt
geoai_rasterio-1.3.11.dist-info/DELVEWHEEL
geoai_rasterio-1.3.11.dist-info/entry_points.txt
geoai_rasterio-1.3.11.dist-info/LICENSE.txt
geoai_rasterio-1.3.11.dist-info/METADATA
geoai_rasterio-1.3.11.dist-info/RECORD
geoai_rasterio-1.3.11.dist-info/top_level.txt
geoai_rasterio-1.3.11.dist-info/WHEEL
