Metadata-Version: 2.1
Name: geoai-rasterio
Version: 1.3.11
Summary: Fast and direct raster I/O for use with Numpy and SciPy
Home-page: https://github.com/rasterio/rasterio
Author: Sean Gillies
Author-email: sean@mapbox.com
License: BSD
Keywords: raster gdal
Classifier: Development Status :: 5 - Production/Stable
Classifier: Intended Audience :: Developers
Classifier: Intended Audience :: Information Technology
Classifier: Intended Audience :: Science/Research
Classifier: License :: OSI Approved :: BSD License
Classifier: Programming Language :: C
Classifier: Programming Language :: Cython
Classifier: Programming Language :: Python :: 3.8
Classifier: Programming Language :: Python :: 3.9
Classifier: Programming Language :: Python :: 3.10
Classifier: Programming Language :: Python :: 3.11
Classifier: Programming Language :: Python :: 3
Classifier: Topic :: Multimedia :: Graphics :: Graphics Conversion
Classifier: Topic :: Scientific/Engineering :: GIS
Requires-Python: >=3.8
License-File: LICENSE.txt
License-File: AUTHORS.txt
Requires-Dist: affine
Requires-Dist: attrs
Requires-Dist: certifi
Requires-Dist: click>=4.0
Requires-Dist: cligj>=0.5
Requires-Dist: numpy
Requires-Dist: snuggs>=1.4.1
Requires-Dist: click-plugins
Requires-Dist: setuptools
Requires-Dist: importlib-metadata; python_version < "3.10"
Provides-Extra: all
Requires-Dist: matplotlib; extra == "all"
Requires-Dist: boto3>=1.2.4; extra == "all"
Requires-Dist: numpydoc; extra == "all"
Requires-Dist: pytest-cov>=2.2.0; extra == "all"
Requires-Dist: ghp-import; extra == "all"
Requires-Dist: ipython>=2.0; extra == "all"
Requires-Dist: sphinx-rtd-theme; extra == "all"
Requires-Dist: pytest>=2.8.2; extra == "all"
Requires-Dist: sphinx; extra == "all"
Requires-Dist: hypothesis; extra == "all"
Requires-Dist: packaging; extra == "all"
Requires-Dist: shapely; python_version < "3.12" and extra == "all"
Provides-Extra: docs
Requires-Dist: ghp-import; extra == "docs"
Requires-Dist: numpydoc; extra == "docs"
Requires-Dist: sphinx; extra == "docs"
Requires-Dist: sphinx-rtd-theme; extra == "docs"
Provides-Extra: ipython
Requires-Dist: ipython>=2.0; extra == "ipython"
Provides-Extra: plot
Requires-Dist: matplotlib; extra == "plot"
Provides-Extra: s3
Requires-Dist: boto3>=1.2.4; extra == "s3"
Provides-Extra: test
Requires-Dist: boto3>=1.2.4; extra == "test"
Requires-Dist: hypothesis; extra == "test"
Requires-Dist: packaging; extra == "test"
Requires-Dist: pytest-cov>=2.2.0; extra == "test"
Requires-Dist: pytest>=2.8.2; extra == "test"
Requires-Dist: shapely; python_version < "3.12" and extra == "test"
